ipynavis_3d_poc/__init__.py
ipynavis_3d_poc/_frontend.py
ipynavis_3d_poc/_version.py
ipynavis_3d_poc/example.py
ipynavis_3d_poc/satellite_monitor.py
ipynavis_3d_poc/labextension/build_log.json
ipynavis_3d_poc/labextension/package.json
ipynavis_3d_poc/labextension/static/06457057fe1b7626859fcc5a69a9c7afc5801ec24b6bc326fd3ade74d929d02d.glb
ipynavis_3d_poc/labextension/static/c222aac9d460adda754ee2f97fba1e34411f10e2b8ca7ca4b9219a50fd476d27.glb
ipynavis_3d_poc/labextension/static/lib_index_js.89dea63974abbc581bbe.js
ipynavis_3d_poc/labextension/static/lib_index_js.89dea63974abbc581bbe.js.map
ipynavis_3d_poc/labextension/static/lib_plugin_js.2327227d238d916eb81b.js
ipynavis_3d_poc/labextension/static/lib_plugin_js.2327227d238d916eb81b.js.map
ipynavis_3d_poc/labextension/static/lib_widget_js.de39947b12ff97e83c40.js
ipynavis_3d_poc/labextension/static/lib_widget_js.de39947b12ff97e83c40.js.map
ipynavis_3d_poc/labextension/static/remoteEntry.948c6b37e7c35d4f501c.js
ipynavis_3d_poc/labextension/static/remoteEntry.948c6b37e7c35d4f501c.js.map
ipynavis_3d_poc/labextension/static/style.js
ipynavis_3d_poc/labextension/static/vendors-node_modules_babylonjs_core_Behaviors_Meshes_fadeInOutBehavior_js-node_modules_babylo-2c1bab.aa8a474055d543a511ad.js
ipynavis_3d_poc/labextension/static/vendors-node_modules_babylonjs_core_Behaviors_Meshes_fadeInOutBehavior_js-node_modules_babylo-2c1bab.aa8a474055d543a511ad.js.map
ipynavis_3d_poc/labextension/static/vendors-node_modules_babylonjs_core_index_js-node_modules_babylonjs_loaders_index_js-node_mod-8e50c6.1089ea4be6f6ebc26b99.js
ipynavis_3d_poc/labextension/static/vendors-node_modules_babylonjs_core_index_js-node_modules_babylonjs_loaders_index_js-node_mod-8e50c6.1089ea4be6f6ebc26b99.js.map
ipynavis_3d_poc/labextension/static/vendors-node_modules_babylonjs_gui_index_js.5ebdaa328e2597c9756e.js
ipynavis_3d_poc/labextension/static/vendors-node_modules_babylonjs_gui_index_js.5ebdaa328e2597c9756e.js.map
ipynavis_3d_poc-0.1.0.dist-info/LICENSE.txt
ipynavis_3d_poc-0.1.0.dist-info/METADATA
ipynavis_3d_poc-0.1.0.dist-info/WHEEL
ipynavis_3d_poc-0.1.0.dist-info/top_level.txt
ipynavis_3d_poc-0.1.0.dist-info/RECORD
